{"id":"2d41bafd-0ac9-4539-84bc-bc766a3d2dca","title":"Types","vault":{"fsPath":"../main/tech","name":"tech"},"type":"note","desc":"","links":[],"anchors":{"clusterip-default":{"type":"header","text":"ClusterIP (default)","value":"clusterip-default","line":8,"column":0},"nodeport":{"type":"header","text":"NodePort","value":"nodeport","line":13,"column":0},"loadbalancer":{"type":"header","text":"LoadBalancer","value":"loadbalancer","line":20,"column":0},"externalname":{"type":"header","text":"ExternalName","value":"externalname","line":23,"column":0}},"fname":"k8s.objects.service.types","updated":1622523620221,"created":1622523601087,"parent":"cac281fe-198d-48ad-b011-2da1928931ca","children":[],"data":{},"contentHash":"a490c9c2a789348a8975fa9f499bbd02","custom":{}}
