{"id":"3102838d-feae-4cc4-a185-c7bea1c205b4","title":"Environment Variables","vault":{"fsPath":"../main/tech","name":"tech"},"type":"note","desc":"","links":[],"anchors":{"environments":{"type":"header","text":"Environments","value":"environments","line":8,"column":0},"environment-variables":{"type":"header","text":"Environment Variables","value":"environment-variables","line":17,"column":0},"export":{"type":"header","text":"Export","value":"export","line":25,"column":0}},"fname":"unix.environments","updated":1620330417970,"created":1615504775847,"parent":"240d9848-b03d-445a-8787-090d79024b6a","children":[],"data":{},"contentHash":"091ddb27882c2c2d0760e6f568f1730f","custom":{}}
