{"id":"3fcb6ae8-f766-4cb6-abd1-38971e471e96","title":"Insert","vault":{"fsPath":"../main/tech","name":"tech"},"type":"note","desc":"","links":[],"anchors":{"insert-mode":{"type":"header","text":"Insert Mode","value":"insert-mode","line":8,"column":0},"insert-normal-mode":{"type":"header","text":"Insert-Normal Mode","value":"insert-normal-mode","line":12,"column":0}},"fname":"vim.modes.insert","updated":1617564382716,"created":1615520259931,"parent":"b79cca0c-d7cd-4513-a338-361d64925267","children":["21a4d5fb-4eda-47ba-b526-ebf7333366e4"],"data":{},"contentHash":"7fa0515d7cd1747752041e15866b042f","custom":{}}
