{"id":"3HZVPhBnB3NbIMXnHuFIp","title":"Overriding","desc":"","updated":1673475138251,"created":1617567125267,"custom":{},"fname":"paradigm.oop.overriding","type":"note","vault":{"fsPath":"../main/tech","name":"tech"},"contentHash":"fe48e09b2ee88121a5b06bab1bb498fe","links":[{"type":"wiki","from":{"fname":"paradigm.oop.overriding","id":"3HZVPhBnB3NbIMXnHuFIp","vaultName":"tech"},"value":"paradigm.oop.polymorphism","alias":"Polymorphism","position":{"start":{"line":4,"column":31,"offset":224},"end":{"line":4,"column":73,"offset":266},"indent":[]},"xvault":false,"sameFile":false,"to":{"fname":"paradigm.oop.polymorphism"}}],"anchors":{},"children":[],"parent":"12a2891c-e26b-47db-9e2e-7a3de90b672b","data":{}}
