{"id":"5BW7Om5FSaxsOGLZw9CsR","title":"Sliding Window","desc":"","updated":1673383315206,"created":1633843919409,"custom":{},"fname":"general.algorithms.patterns.sliding-window","type":"note","vault":{"fsPath":"../main/tech","name":"tech"},"contentHash":"9da0fadb08b58f3d0722d6ad13ddb1be","links":[{"from":{"fname":"general.patterns.streaming.window","id":"n8usaompbr8xl7pzw869fgy","vaultName":"tech"},"type":"backlink","position":{"start":{"line":14,"column":8,"offset":350},"end":{"line":14,"column":79,"offset":421},"indent":[]},"value":"general.algorithms.patterns.sliding-window"}],"anchors":{"example-calculate-averages":{"type":"header","text":"Example: Calculate averages","value":"example-calculate-averages","line":12,"column":0,"depth":3}},"children":[],"parent":"FL3Vi4Vss0wSZoLTnSvRz","data":{}}
