{"id":"6rd2UlBxaM4Uc41t6VY63","title":"Load Testing","desc":"","updated":1637782938873,"created":1637778537999,"custom":{},"fname":"testing.method.load","type":"note","vault":{"fsPath":"../main/tech","name":"tech"},"contentHash":"5725612525fc988f47776789b9e1d3da","links":[{"type":"wiki","from":{"fname":"testing.method.load","id":"6rd2UlBxaM4Uc41t6VY63","vaultName":"tech"},"value":"network.osi-model","alias":"OSI","position":{"start":{"line":16,"column":39,"offset":1119},"end":{"line":16,"column":64,"offset":1144},"indent":[]},"xvault":false,"sameFile":false,"to":{"fname":"network.osi-model"}},{"type":"wiki","from":{"fname":"testing.method.load","id":"6rd2UlBxaM4Uc41t6VY63","vaultName":"tech"},"value":"k6","position":{"start":{"line":59,"column":3,"offset":5250},"end":{"line":59,"column":9,"offset":5256},"indent":[]},"xvault":false,"sameFile":false,"to":{"fname":"k6"}},{"from":{"fname":"k6","id":"z8ie0xjogb6ht7gzowav5xr","vaultName":"tech"},"type":"backlink","position":{"start":{"line":2,"column":49,"offset":49},"end":{"line":2,"column":85,"offset":85},"indent":[]},"value":"testing.method.load"},{"from":{"fname":"deploy.performance","id":"j0ZVTb0cyNKaYUu1g6a2g","vaultName":"tech"},"type":"backlink","position":{"start":{"line":13,"column":25,"offset":536},"end":{"line":13,"column":48,"offset":559},"indent":[]},"value":"testing.method.load"},{"from":{"fname":"testing.method.smoke","id":"oJKMYgXk2Z9RXThzrMh8j","vaultName":"tech"},"type":"backlink","position":{"start":{"line":2,"column":24,"offset":24},"end":{"line":2,"column":57,"offset":57},"indent":[]},"value":"testing.method.load"}],"anchors":{"what-a-load-testing-frameworktool-does":{"type":"header","text":"What a Load Testing framework/tool does","value":"what-a-load-testing-frameworktool-does","line":40,"column":0,"depth":3},"shopping-cart-example":{"type":"header","text":"Shopping cart example","value":"shopping-cart-example","line":49,"column":0,"depth":3},"analysis":{"type":"header","text":"Analysis","value":"analysis","line":58,"column":0,"depth":3},"tools":{"type":"header","text":"Tools","value":"tools","line":64,"column":0,"depth":2}},"children":[],"parent":"ZLN1ACLozCBSkyy2qWivT","data":{}}
