{"id":"7Hd68M5niADEkip4CdU85","title":"Infrastructure-as-Code","desc":"","updated":1641597049939,"created":1641315454512,"custom":{},"fname":"devops.IaC","type":"note","vault":{"fsPath":"../main/tech","name":"tech"},"contentHash":"b7f73d66b13fd03fc6feae9d7405bea7","links":[{"type":"wiki","from":{"fname":"devops.IaC","id":"7Hd68M5niADEkip4CdU85","vaultName":"tech"},"value":"terraform","alias":"Terraform","position":{"start":{"line":19,"column":3,"offset":1025},"end":{"line":19,"column":26,"offset":1048},"indent":[]},"xvault":false,"sameFile":false,"to":{"fname":"terraform"}},{"from":{"fname":"devops","vaultName":"tech"},"type":"backlink","position":{"start":{"line":7,"column":1,"offset":903},"end":{"line":7,"column":19,"offset":921},"indent":[]},"value":"devops.IaC"},{"from":{"fname":"devops.IaC.gitops","vaultName":"tech"},"type":"backlink","position":{"start":{"line":4,"column":67,"offset":339},"end":{"line":4,"column":85,"offset":357},"indent":[]},"value":"devops.IaC"},{"from":{"fname":"devops.IaC.gitops","vaultName":"tech"},"type":"backlink","position":{"start":{"line":7,"column":36,"offset":537},"end":{"line":7,"column":54,"offset":555},"indent":[]},"value":"devops.IaC"},{"from":{"fname":"devops.IaC.gitops","vaultName":"tech"},"type":"backlink","position":{"start":{"line":26,"column":3,"offset":2352},"end":{"line":26,"column":21,"offset":2370},"indent":[]},"value":"devops.IaC"}],"anchors":{"examples":{"type":"header","text":"Examples","value":"examples","line":18,"column":0,"depth":3}},"children":["lBasXzi1eHzGwL2pEuOv8"],"parent":"RgE0mZLaUjPftFPZsiAoe","data":{}}
