{"id":"9oglq5pogy5inbt24yjk3hp","title":"Middleware","desc":"","updated":1651597085786,"created":1651596904819,"custom":{},"fname":"nestjs.middleware","type":"note","vault":{"fsPath":"../main/tech","name":"tech"},"contentHash":"ac32446d31f8a695e501f7bf3608ac19","links":[{"type":"wiki","from":{"fname":"nestjs.middleware","id":"9oglq5pogy5inbt24yjk3hp","vaultName":"tech"},"value":"express.middleware","alias":"Express middleware","position":{"start":{"line":2,"column":36,"offset":36},"end":{"line":2,"column":77,"offset":77},"indent":[]},"xvault":false,"sameFile":false,"to":{"fname":"express.middleware"}},{"from":{"fname":"nestjs","id":"613syb18hb3v0u1ydvor7ru","vaultName":"tech"},"type":"backlink","position":{"start":{"line":102,"column":1,"offset":6083},"end":{"line":102,"column":23,"offset":6105},"indent":[]},"value":"nestjs.middleware"}],"anchors":{},"children":[],"parent":"613syb18hb3v0u1ydvor7ru","data":{}}
