{"id":"9YspU1V7eJ9rz91kiTrUN","title":"Types","desc":"","updated":1622523620221,"created":1622523601087,"custom":{},"fname":"k8s.objects.service.types","type":"note","vault":{"fsPath":"../main/tech","name":"tech"},"contentHash":"b8f696c03474682fe0e81ec3621f32ea","links":[],"anchors":{"clusterip-default":{"type":"header","text":"ClusterIP (default)","value":"clusterip-default","line":8,"column":0,"depth":4},"nodeport":{"type":"header","text":"NodePort","value":"nodeport","line":13,"column":0,"depth":4},"loadbalancer":{"type":"header","text":"LoadBalancer","value":"loadbalancer","line":20,"column":0,"depth":4},"externalname":{"type":"header","text":"ExternalName","value":"externalname","line":23,"column":0,"depth":4}},"children":[],"parent":"ryBzcGWSKyybRXnyKxteV","data":{}}
