{"id":"aKUNicL6BcYzCtaWOR8wH","title":"CLI","desc":"","updated":1666898662438,"created":1615267823705,"custom":{},"fname":"docker.image.cli","type":"note","vault":{"fsPath":"../main/tech","name":"tech"},"contentHash":"c83e5f87870b93abd396da4ef970338b","links":[],"anchors":{"docker-images":{"type":"header","text":"docker images","value":"docker-images","line":8,"column":0,"depth":3},"docker-build":{"type":"header","text":"docker build","value":"docker-build","line":11,"column":0,"depth":3},"inject-env-variables-into-the-dockerfile-build-process":{"type":"header","text":"Inject env variables into the Dockerfile build process","value":"inject-env-variables-into-the-dockerfile-build-process","line":14,"column":0,"depth":3},"build-image":{"type":"header","text":"Build image","value":"build-image","line":17,"column":0,"depth":2}},"children":[],"parent":"SQwuv6ixxiQtYGEQnoSZo","data":{}}
