{"id":"CSePBQ6q7qhowKESqVwt7","title":"Graphql","desc":"","updated":1647532086777,"created":1618005049001,"custom":{"stub":false},"fname":"graphql","type":"note","vault":{"fsPath":"../main/tech","name":"tech"},"contentHash":"ba636f6be96f8f5721d40d467c72581b","links":[{"type":"wiki","from":{"fname":"graphql","id":"CSePBQ6q7qhowKESqVwt7","vaultName":"tech"},"value":"graphql.documents","alias":"document","position":{"start":{"line":20,"column":18,"offset":1528},"end":{"line":20,"column":48,"offset":1558},"indent":[]},"xvault":false,"sameFile":false,"to":{"fname":"graphql.documents"}},{"type":"wiki","from":{"fname":"graphql","id":"CSePBQ6q7qhowKESqVwt7","vaultName":"tech"},"value":"graphql.ast","position":{"start":{"line":20,"column":105,"offset":1615},"end":{"line":20,"column":120,"offset":1630},"indent":[]},"xvault":false,"sameFile":false,"to":{"fname":"graphql.ast"}},{"type":"wiki","from":{"fname":"graphql","id":"CSePBQ6q7qhowKESqVwt7","vaultName":"tech"},"value":"apollo.federation","position":{"start":{"line":59,"column":63,"offset":3370},"end":{"line":59,"column":84,"offset":3391},"indent":[]},"xvault":false,"sameFile":false,"to":{"fname":"apollo.federation"}},{"from":{"fname":"sanity.groq","id":"MXSnfG3Cey0BozII19IQY","vaultName":"tech"},"type":"backlink","position":{"start":{"line":2,"column":111,"offset":111},"end":{"line":2,"column":130,"offset":130},"indent":[]},"value":"graphql"}],"anchors":{"overview":{"type":"header","text":"Overview","value":"overview","line":8,"column":0,"depth":2},"phases":{"type":"header","text":"Phases","value":"phases","line":24,"column":0,"depth":3},"between-the-client-and-app-server":{"type":"header","text":"Between the client and app server","value":"between-the-client-and-app-server","line":31,"column":0,"depth":2},"selection-sets":{"type":"header","text":"Selection Sets","value":"selection-sets","line":37,"column":0,"depth":2},"distributed-graphql":{"type":"header","text":"Distributed graphql","value":"distributed-graphql","line":61,"column":0,"depth":3},"ue-resources":{"type":"header","text":"UE Resources","value":"ue-resources","line":69,"column":0,"depth":3}},"children":["yy5ylwnBHCQR8ef9dxldx","pLjPOq1zALpEjYmeoRcI4","3HS5EsWWVemFJzEgHmi3j","YrV9FViC2kjwO2LhRHFzT","BbFQyn0yaYxYLIwA61LSm","u2t1TIqBz2MPrlAfzbApK","uvNhRB7dp5lugyo3sUezc","LvwyDhSirG3TuxN3EX6T6","FMQ44lIBsK1ugnuh54RKE","q3ZzZUfqn8nRhWQXBW8P1","e8c0cb48-6247-4280-8717-5c389ee66659","1K0gApOQ1HbLV2GYrQRLU","yUM3CM4TlWpQdBOQ9WBof","cerrwR0xwq4a7OLikDo2k","VwLlDck5sKxp2KDOOWZCb"],"parent":"olZIVfSs2uLLr3BppFh4K","data":{}}
