{"id":"G1aFACZB2ooWGMGwyd3ZW","title":"Mongoose","desc":"","updated":1645600856318,"created":1615184194611,"custom":{},"fname":"mongoose","type":"note","vault":{"fsPath":"../main/tech","name":"tech"},"contentHash":"0c0aea36f32a5fdedfa98ef0be45f619","links":[],"anchors":{"hooks-aka-middleware":{"type":"header","text":"Hooks (a.k.a. Middleware)","value":"hooks-aka-middleware","line":10,"column":0,"depth":1},"pre-hooks":{"type":"header","text":"pre-hooks","value":"pre-hooks","line":20,"column":0,"depth":2},"serial":{"type":"header","text":"Serial","value":"serial","line":22,"column":0,"depth":3},"parallel":{"type":"header","text":"Parallel","value":"parallel","line":37,"column":0,"depth":3},"post-hooks":{"type":"header","text":"post-hooks","value":"post-hooks","line":50,"column":0,"depth":2},"types-of-middleware":{"type":"header","text":"Types of middleware","value":"types-of-middleware","line":64,"column":0,"depth":2},"document-mw":{"type":"header","text":"Document MW","value":"document-mw","line":65,"column":0,"depth":3},"model-mw":{"type":"header","text":"Model MW","value":"model-mw","line":80,"column":0,"depth":3},"query-mw":{"type":"header","text":"Query MW","value":"query-mw","line":82,"column":0,"depth":3},"aggregate-mw":{"type":"header","text":"Aggregate MW","value":"aggregate-mw","line":104,"column":0,"depth":3},"populate":{"type":"header","text":"Populate","value":"populate","line":110,"column":0,"depth":1},"schemas":{"type":"header","text":"Schemas","value":"schemas","line":155,"column":0,"depth":1},"instance-methods":{"type":"header","text":"Instance Methods","value":"instance-methods","line":156,"column":0,"depth":2},"static-methods":{"type":"header","text":"Static Methods","value":"static-methods","line":179,"column":0,"depth":2},"query-helper":{"type":"header","text":"Query Helper","value":"query-helper","line":191,"column":0,"depth":2},"virtual":{"type":"header","text":"Virtual","value":"virtual","line":207,"column":0,"depth":2},"accessing-the-parent-documents-from-the-child-document":{"type":"header","text":"Accessing the parent documents from the child document","value":"accessing-the-parent-documents-from-the-child-document","line":216,"column":0,"depth":3},"nested-routes":{"type":"header","text":"Nested routes","value":"nested-routes","line":228,"column":0,"depth":2},"improving-read-performance-with-indices":{"type":"header","text":"Improving Read Performance with Indices","value":"improving-read-performance-with-indices","line":232,"column":0,"depth":2},"e-resources":{"type":"header","text":"E Resources","value":"e-resources","line":237,"column":0,"depth":1}},"children":[],"parent":"olZIVfSs2uLLr3BppFh4K","data":{}}
