{"id":"GkdMprLUe4QQULBxmGN6V","title":"Ember","desc":"","updated":1615444727056,"created":1615444727056,"custom":{},"fname":"ember","type":"note","vault":{"fsPath":"../main/tech","name":"tech"},"contentHash":"7c65c6d4e2fddb7f2c07910ffe00bf1d","links":[{"type":"wiki","from":{"fname":"ember","id":"GkdMprLUe4QQULBxmGN6V","vaultName":"tech"},"value":"user.tracked","alias":"@tracked","position":{"start":{"line":75,"column":79,"offset":3859},"end":{"line":75,"column":87,"offset":3867},"indent":[]},"xvault":false,"to":{"fname":"user.tracked"}}],"anchors":{"overview":{"type":"header","text":"Overview","value":"overview","line":8,"column":0,"depth":1},"decorators":{"type":"header","text":"Decorators","value":"decorators","line":16,"column":0,"depth":1},"types":{"type":"header","text":"Types","value":"types","line":22,"column":0,"depth":2},"anatomy-of-ember-app":{"type":"header","text":"Anatomy of Ember app","value":"anatomy-of-ember-app","line":33,"column":0,"depth":1},"models":{"type":"header","text":"Models","value":"models","line":41,"column":0,"depth":2},"templates":{"type":"header","text":"Templates","value":"templates","line":47,"column":0,"depth":2},"applicationhbs":{"type":"header","text":"application.hbs","value":"applicationhbs","line":51,"column":0,"depth":3},"components":{"type":"header","text":"Components","value":"components","line":55,"column":0,"depth":2},"namespaced-components":{"type":"header","text":"Namespaced components","value":"namespaced-components","line":62,"column":0,"depth":3},"class-components":{"type":"header","text":"Class components","value":"class-components","line":73,"column":0,"depth":3},"block-parameters":{"type":"header","text":"Block parameters","value":"block-parameters","line":83,"column":0,"depth":4},"provider-component":{"type":"header","text":"Provider component","value":"provider-component","line":101,"column":0,"depth":4},"routes":{"type":"header","text":"Routes","value":"routes","line":107,"column":0,"depth":2},"model-hook":{"type":"header","text":"Model hook","value":"model-hook","line":108,"column":0,"depth":3},"services":{"type":"header","text":"Services","value":"services","line":112,"column":0,"depth":2},"store-service":{"type":"header","text":"Store service","value":"store-service","line":118,"column":0,"depth":3},"controller":{"type":"header","text":"Controller","value":"controller","line":132,"column":0,"depth":2},"libraries":{"type":"header","text":"Libraries","value":"libraries","line":149,"column":0,"depth":1},"ember-data":{"type":"header","text":"Ember Data","value":"ember-data","line":150,"column":0,"depth":2},"structure":{"type":"header","text":"Structure","value":"structure","line":187,"column":0,"depth":1},"tests":{"type":"header","text":"Tests","value":"tests","line":190,"column":0,"depth":1},"mirage":{"type":"header","text":"Mirage","value":"mirage","line":194,"column":0,"depth":1},"factories":{"type":"header","text":"Factories","value":"factories","line":195,"column":0,"depth":2}},"children":[],"parent":"olZIVfSs2uLLr3BppFh4K","data":{}}
