{"id":"hEG7YxFDbOJ2PM8cVy66M","title":"useCallback","desc":"","updated":1650292825395,"created":1615070458802,"custom":{},"fname":"react.lang.hooks.useCallback","type":"note","vault":{"fsPath":"../main/tech","name":"tech"},"contentHash":"a9486a7a81c3b97c4868b48484cc9c29","links":[{"type":"wiki","from":{"fname":"react.lang.hooks.useCallback","id":"hEG7YxFDbOJ2PM8cVy66M","vaultName":"tech"},"value":"react.lang.hooks.useMemo","alias":"useMemo","position":{"start":{"line":4,"column":33,"offset":111},"end":{"line":4,"column":69,"offset":147},"indent":[]},"xvault":false,"sameFile":false,"to":{"fname":"react.lang.hooks.useMemo"}},{"from":{"fname":"react.lang.hooks.useMemo","vaultName":"tech"},"type":"backlink","position":{"start":{"line":5,"column":18,"offset":137},"end":{"line":5,"column":62,"offset":181},"indent":[]},"value":"react.lang.hooks.useCallback","alias":"useCallback"}],"anchors":{"usecallback":{"type":"header","text":"useCallback","value":"usecallback","line":18,"column":0,"depth":2}},"children":[],"parent":"59dedd99-adb7-430f-a849-b303425e3209","data":{}}
