{"id":"htdliYukykAPcYTqQGJWz","title":"Buffer","desc":"","updated":1615525149986,"created":1615519681361,"custom":{"stub":false},"fname":"vim.nav.buffer","type":"note","vault":{"fsPath":"../main/tech","name":"tech"},"contentHash":"736fb3022b7c5f6281e4a665357261f5","links":[],"anchors":{"buffer-navigation":{"type":"header","text":"Buffer Navigation","value":"buffer-navigation","line":8,"column":0,"depth":1},"":{"type":"header","text":"","value":"","line":9,"column":0,"depth":2},"returning-to-previous-locations":{"type":"header","text":"Returning to previous locations","value":"returning-to-previous-locations","line":36,"column":0,"depth":2}},"children":["ZeispkHs1AYUHCxGutuiD","vMKPcUVaOHbMdAoVJsb9L"],"parent":"b0f9ffe8-9af0-423c-9021-07f026cbbce7","data":{}}
