{"id":"ifb8lv2u408wbatjuzoyfxk","title":"Battery","desc":"","updated":1649117627073,"created":1649117627073,"custom":{},"fname":"hardware.battery","type":"note","vault":{"fsPath":"../main/tech","name":"tech"},"contentHash":"a206dbee718369f702678fbe410e0f11","links":[],"anchors":{"why-batteries-drain-faster-when-network-connection-is-bad":{"type":"header","text":"Why batteries drain faster when network connection is bad","value":"why-batteries-drain-faster-when-network-connection-is-bad","line":8,"column":0,"depth":3}},"children":[],"parent":"laZ4OfLhZNK1Kuy6GaWUr","data":{}}
