{"id":"jiITIvU42MBAYcbXheWwI","title":"Index","desc":"","updated":1653506706315,"created":1615340679408,"custom":{},"fname":"db.strategies.index","type":"note","vault":{"fsPath":"../main/tech","name":"tech"},"contentHash":"f9535909da92a268d38ac5f78a8f48e6","links":[{"type":"wiki","from":{"fname":"db.strategies.index","id":"jiITIvU42MBAYcbXheWwI","vaultName":"tech"},"value":"db.distributed.partitioning","alias":"partitioning","position":{"start":{"line":34,"column":64,"offset":2863},"end":{"line":34,"column":108,"offset":2907},"indent":[]},"xvault":false,"sameFile":false,"to":{"fname":"db.distributed.partitioning"}},{"type":"wiki","from":{"fname":"db.strategies.index","id":"jiITIvU42MBAYcbXheWwI","vaultName":"tech"},"value":"general.lang.data-structs.tree.B","alias":"B-tree","position":{"start":{"line":55,"column":84,"offset":5004},"end":{"line":55,"column":127,"offset":5047},"indent":[]},"xvault":false,"sameFile":false,"to":{"fname":"general.lang.data-structs.tree.B"}},{"type":"wiki","from":{"fname":"db.strategies.index","id":"jiITIvU42MBAYcbXheWwI","vaultName":"tech"},"value":"db.olap-oltp","alias":"OLAP","position":{"start":{"line":71,"column":40,"offset":7049},"end":{"line":71,"column":61,"offset":7070},"indent":[]},"xvault":false,"sameFile":false,"to":{"fname":"db.olap-oltp"}},{"type":"wiki","from":{"fname":"db.strategies.index","id":"jiITIvU42MBAYcbXheWwI","vaultName":"tech"},"value":"general.lang.data-structs.hash-table","alias":"hash map","position":{"start":{"line":87,"column":111,"offset":7784},"end":{"line":87,"column":160,"offset":7833},"indent":[]},"xvault":false,"sameFile":false,"to":{"fname":"general.lang.data-structs.hash-table"}},{"type":"wiki","from":{"fname":"db.strategies.index","id":"jiITIvU42MBAYcbXheWwI","vaultName":"tech"},"value":"general.lang.data-structs.tree.B","alias":"general.lang.data-structs.tree.B","position":{"start":{"line":113,"column":1,"offset":8462},"end":{"line":113,"column":37,"offset":8498},"indent":[]},"xvault":false,"sameFile":false,"to":{"fname":"general.lang.data-structs.tree.B"}},{"from":{"fname":"db","vaultName":"tech"},"type":"backlink","position":{"start":{"line":12,"column":48,"offset":471},"end":{"line":12,"column":77,"offset":500},"indent":[]},"value":"db.strategies.index","alias":"index"},{"from":{"fname":"elastic-search","vaultName":"tech"},"type":"backlink","position":{"start":{"line":22,"column":11,"offset":1590},"end":{"line":22,"column":42,"offset":1621},"indent":[]},"value":"db.strategies.index","alias":"indexes"},{"from":{"fname":"couchdb.design-doc","vaultName":"tech"},"type":"backlink","position":{"start":{"line":2,"column":36,"offset":36},"end":{"line":2,"column":67,"offset":67},"indent":[]},"value":"db.strategies.index","alias":"indexes"},{"from":{"fname":"dns.domain","vaultName":"tech"},"type":"backlink","position":{"start":{"line":28,"column":26,"offset":1572},"end":{"line":28,"column":57,"offset":1603},"indent":[]},"value":"db.strategies.index","alias":"indexes"},{"from":{"fname":"couchdb.design-doc.view","vaultName":"tech"},"type":"backlink","position":{"start":{"line":6,"column":30,"offset":358},"end":{"line":6,"column":61,"offset":389},"indent":[]},"value":"db.strategies.index","alias":"indexes"},{"from":{"fname":"general.patterns.map-reduce","vaultName":"tech"},"type":"backlink","position":{"start":{"line":19,"column":29,"offset":1338},"end":{"line":19,"column":60,"offset":1369},"indent":[]},"value":"db.strategies.index","alias":"indexes"},{"from":{"fname":"pg.lang.index","vaultName":"tech"},"type":"backlink","position":{"start":{"line":2,"column":32,"offset":32},"end":{"line":2,"column":61,"offset":61},"indent":[]},"value":"db.strategies.index","alias":"index"},{"from":{"fname":"pg.lang.index","vaultName":"tech"},"type":"backlink","position":{"start":{"line":34,"column":1,"offset":2424},"end":{"line":34,"column":35,"offset":2458},"indent":[]},"value":"db.strategies.index","alias":"Index Docs"},{"from":{"fname":"general.lang.data-structs.tree.B","vaultName":"tech"},"type":"backlink","position":{"start":{"line":45,"column":53,"offset":3943},"end":{"line":45,"column":84,"offset":3974},"indent":[]},"value":"db.strategies.index","alias":"indexes"}],"anchors":{"what-is-it":{"type":"header","text":"What is it?","value":"what-is-it","line":8,"column":0,"depth":2},"primary-index":{"type":"header","text":"Primary Index","value":"primary-index","line":25,"column":0,"depth":3},"secondary-index":{"type":"header","text":"Secondary Index","value":"secondary-index","line":28,"column":0,"depth":3},"umbrella-analogy":{"type":"header","text":"Umbrella Analogy","value":"umbrella-analogy","line":43,"column":0,"depth":3},"textbook-analogy":{"type":"header","text":"Textbook Analogy","value":"textbook-analogy","line":47,"column":0,"depth":3},"why-use-it":{"type":"header","text":"Why use it?","value":"why-use-it","line":50,"column":0,"depth":2},"how-does-it-work":{"type":"header","text":"How does it work?","value":"how-does-it-work","line":79,"column":0,"depth":2},"types":{"type":"header","text":"Types","value":"types","line":85,"column":0,"depth":2},"hash-index":{"type":"header","text":"Hash Index","value":"hash-index","line":86,"column":0,"depth":3},"b-tree":{"type":"header","text":"B-Tree","value":"b-tree","line":118,"column":0,"depth":3},"clustered-index":{"type":"header","text":"Clustered Index","value":"clustered-index","line":123,"column":0,"depth":3},"non-clustered-index":{"type":"header","text":"Non-clustered Index","value":"non-clustered-index","line":133,"column":0,"depth":3},"multi-column-index":{"type":"header","text":"Multi-column Index","value":"multi-column-index","line":138,"column":0,"depth":3},"concatenated-index":{"type":"header","text":"Concatenated Index","value":"concatenated-index","line":141,"column":0,"depth":4},"multi-dimensional-index":{"type":"header","text":"Multi-dimensional Index","value":"multi-dimensional-index","line":146,"column":0,"depth":3},"example-location-queries":{"type":"header","text":"Example: location queries","value":"example-location-queries","line":149,"column":0,"depth":4},"other-examples":{"type":"header","text":"Other examples","value":"other-examples","line":164,"column":0,"depth":4},"full-text-search-and-fuzzy-indexes":{"type":"header","text":"Full-text search and Fuzzy Indexes","value":"full-text-search-and-fuzzy-indexes","line":169,"column":0,"depth":3}},"children":[],"parent":"DNdF8pLi53EjMklhKQ7WA","data":{}}
