{"id":"jQfMZULJJrSF04JMQcIgP","title":"Binary","desc":"","updated":1679588284055,"created":1633614583391,"custom":{},"fname":"general.lang.data-structs.tree.binary","type":"note","vault":{"fsPath":"../main/tech","name":"tech"},"contentHash":"f62a7630e7c75711581ad214b3a6b87d","links":[{"type":"wiki","from":{"fname":"general.lang.data-structs.tree.binary","id":"jQfMZULJJrSF04JMQcIgP","vaultName":"tech"},"value":"general.algorithms.big-o","alias":"time complexity","position":{"start":{"line":110,"column":25,"offset":4155},"end":{"line":110,"column":69,"offset":4199},"indent":[]},"xvault":false,"sameFile":false,"to":{"fname":"general.algorithms.big-o"}},{"from":{"fname":"general.lang.data-structs.heap","id":"YZrw2KGw9jYZZLx3yn8qt","vaultName":"tech"},"type":"backlink","position":{"start":{"line":2,"column":33,"offset":33},"end":{"line":2,"column":87,"offset":87},"indent":[]},"value":"general.lang.data-structs.tree.binary"},{"from":{"fname":"general.lang.data-structs.tree.B","id":"UE8OS2s713jEk2CmjiAet","vaultName":"tech"},"type":"backlink","position":{"start":{"line":2,"column":10,"offset":10},"end":{"line":2,"column":63,"offset":63},"indent":[]},"value":"general.lang.data-structs.tree.binary"}],"anchors":{"binary-search-tree-bst":{"type":"header","text":"Binary Search Tree (BST)","value":"binary-search-tree-bst","line":12,"column":0,"depth":1},"implementing-a-bst-in-typescript":{"type":"header","text":"Implementing a BST in Typescript","value":"implementing-a-bst-in-typescript","line":24,"column":0,"depth":2},"finding-a-node-by-key":{"type":"header","text":"Finding a node by key","value":"finding-a-node-by-key","line":92,"column":0,"depth":3},"inserting-into-tree":{"type":"header","text":"Inserting into tree","value":"inserting-into-tree","line":98,"column":0,"depth":3},"advantages":{"type":"header","text":"Advantages","value":"advantages","line":111,"column":0,"depth":4},"traversal-types":{"type":"header","text":"Traversal types","value":"traversal-types","line":118,"column":0,"depth":3},"storing-a-bst":{"type":"header","text":"\"Storing\" a BST","value":"storing-a-bst","line":123,"column":0,"depth":3}},"children":[],"parent":"4lEin54l6IUwYZFNsijVg","data":{}}
