{"id":"Luqwbu4DMVwVSCJuJaDBp","title":"Context Object","desc":"","updated":1643899779520,"created":1642629043212,"custom":{},"fname":"graphql.server.resolver.context","type":"note","vault":{"fsPath":"../main/tech","name":"tech"},"contentHash":"2ec7544ccc99dbd31d831186c9b35568","links":[{"type":"wiki","from":{"fname":"graphql.server.resolver.context","id":"Luqwbu4DMVwVSCJuJaDBp","vaultName":"tech"},"value":"general.patterns.data-source","alias":"data sources","position":{"start":{"line":10,"column":3,"offset":437},"end":{"line":10,"column":48,"offset":482},"indent":[]},"xvault":false,"sameFile":false,"to":{"fname":"general.patterns.data-source"}},{"from":{"fname":"graphql.server.resolver","id":"GDD7xPlpQqrQnmwcDXUoa","vaultName":"tech"},"type":"backlink","position":{"start":{"line":42,"column":1,"offset":3173},"end":{"line":42,"column":37,"offset":3209},"indent":[]},"value":"graphql.server.resolver.context"}],"anchors":{},"children":[],"parent":"GDD7xPlpQqrQnmwcDXUoa","data":{}}
