{"id":"QyhBiiMo8hlLxdGY9WX7K","title":"Rebase","desc":"","updated":1671308222351,"created":1616785039322,"custom":{"stub":false},"fname":"git.cli.rebase","type":"note","vault":{"fsPath":"../main/tech","name":"tech"},"contentHash":"abf8d8d72b6871eac2ffd0ff47ff5b72","links":[],"anchors":{"process":{"type":"header","text":"Process","value":"process","line":31,"column":0,"depth":2},"behind-the-scenes":{"type":"header","text":"Behind the Scenes","value":"behind-the-scenes","line":36,"column":0,"depth":3},"process-1":{"type":"header","text":"Process","value":"process-1","line":43,"column":0,"depth":3},"conflicts":{"type":"header","text":"Conflicts","value":"conflicts","line":50,"column":0,"depth":4},"when-to-use-rebase":{"type":"header","text":"When to use rebase","value":"when-to-use-rebase","line":54,"column":0,"depth":3},"drawbacks-to-rebase":{"type":"header","text":"Drawbacks to rebase","value":"drawbacks-to-rebase","line":61,"column":0,"depth":3},"shared-branches":{"type":"header","text":"Shared branches","value":"shared-branches","line":68,"column":0,"depth":4},"long-lived-feature-branches-llfb":{"type":"header","text":"Long-lived Feature Branches (LLFB)","value":"long-lived-feature-branches-llfb","line":71,"column":0,"depth":2},"e-resources":{"type":"header","text":"E Resources","value":"e-resources","line":74,"column":0,"depth":1}},"children":["R6NsoPat1BmEDwycbn5q6"],"parent":"wgiwNFC5iqnWdSZT9yYET","data":{}}
