{"id":"vEO5b64iCKA3QYhvBR2zh","title":"Light","vault":{"fsPath":"../main/tech","name":"tech"},"type":"note","desc":"","links":[],"anchors":{"directional-light":{"type":"header","text":"Directional Light","value":"directional-light","line":8,"column":0},"spot-light":{"type":"header","text":"Spot light","value":"spot-light","line":12,"column":0},"resources":{"type":"header","text":"Resources","value":"resources","line":15,"column":0}},"fname":"unity.go.light","updated":1629071302194,"created":1629071116983,"parent":"M9fcbyYJuu1HLvk4qLF9i","children":[],"data":{},"contentHash":"53119350c83c175ccce2fb07ba64081c","custom":{}}
