{"id":"YF8NReglnt0n2wSbDsva5","title":"Stack","desc":"","updated":1645600707086,"created":1615528770337,"custom":{},"fname":"memory.stack","type":"note","vault":{"fsPath":"../main/tech","name":"tech"},"contentHash":"8f47af9e049a7e7b8689f0d7003d4eed","links":[{"type":"wiki","from":{"fname":"memory.stack","id":"YF8NReglnt0n2wSbDsva5","vaultName":"tech"},"value":"memory.heap","alias":"heap","position":{"start":{"line":2,"column":15,"offset":15},"end":{"line":2,"column":35,"offset":35},"indent":[]},"xvault":false,"sameFile":false,"to":{"fname":"memory.heap"}},{"from":{"fname":"memory","vaultName":"tech"},"type":"backlink","position":{"start":{"line":2,"column":129,"offset":129},"end":{"line":2,"column":151,"offset":151},"indent":[]},"value":"memory.stack","alias":"Stack"},{"from":{"fname":"memory.heap","vaultName":"tech"},"type":"backlink","position":{"start":{"line":2,"column":15,"offset":15},"end":{"line":2,"column":37,"offset":37},"indent":[]},"value":"memory.stack","alias":"stack"},{"from":{"fname":"memory.heap","vaultName":"tech"},"type":"backlink","position":{"start":{"line":15,"column":57,"offset":898},"end":{"line":15,"column":80,"offset":921},"indent":[]},"value":"memory.stack","alias":"stacks"}],"anchors":{},"children":[],"parent":"I01hENHnh8Tqu3Ok8sLzG","data":{}}
